vswhere/__init__.py
vswhere-1.3.0.dist-info/LICENSE
vswhere-1.3.0.dist-info/METADATA
vswhere-1.3.0.dist-info/WHEEL
vswhere-1.3.0.dist-info/top_level.txt
vswhere-1.3.0.dist-info/RECORD
