Metadata-Version: 2.1
Name: vswhere
Version: 1.3.0
Summary: Interface to Microsoft's Visual Studio locator tool, vswhere
Home-page: https://github.com/ChaosinaCan/pyvswhere
Author: Joel Spadin
Author-email: joelspadin@gmail.com
License: MIT
Platform: UNKNOWN
Classifier: License :: OSI Approved :: MIT License
Classifier: Operating System :: Microsoft :: Windows
Classifier: Programming Language :: Python :: 2.7
Classifier: Programming Language :: Python :: 3
Classifier: Topic :: Text Editors :: Integrated Development Environments (IDE)
